tondor-tool/__init__.py
tondor-tool/creodias.py
tondor-tool/geo.py
tondor-tool/grassland.py
tondor-tool/lsru.py
tondor-tool/postgres.py
tondortools/__init__.py
tondortools/creodias.py
tondortools/geo.py
tondortools/grassland.py
tondortools/input_parser.py
tondortools/logging_config.py
tondortools/lsru.py
tondortools/object.py
tondortools/postgres.py
tondortools/preprocessing.py
tondortools/raster.py
tondortools/stat.py
tondortools/subtiling.py
tondortools/tiling.py
tondortools/tool.py
tondortools/tiles_gpkg/__init__.py
tondortools-1.0.55.dist-info/METADATA
tondortools-1.0.55.dist-info/WHEEL
tondortools-1.0.55.dist-info/top_level.txt
tondortools-1.0.55.dist-info/RECORD
