Metadata-Version: 2.1
Name: tondortools
Version: 1.0.55
Summary: Package inludes tools for Tondor
Home-page: https://github.com/gisat/tondor_tools
Author: Michal Opetal, Sivasankar Arul
Author-email: michal.opletal@gisat.cz, sivasankar.arul@gisat.cz
License: MIT
Classifier: License :: OSI Approved :: MIT License
Classifier: Programming Language :: Python :: 3
Classifier: Programming Language :: Python :: 3.9
